Metadata-Version: 2.1
Name: emarsysauthenticator
Version: 0.0.1
Summary: Python helper to easily create X-WSSE header for Authentication with Emarsys RESTful API
Home-page: https://github.com/datapip/emarsysauthenticator
Author: Philipp Jaeckle
Author-email: p.a.jaeckle@gmail.com
License: UNKNOWN
Platform: UNKNOWN
Classifier: Programming Language :: Python :: 3
Classifier: License :: OSI Approved :: MIT License
Classifier: Operating System :: OS Independent
